LICENSE
MANIFEST.in
setup.py
redlock/__init__.py
redlock/lock.py
redlock_rf.egg-info/PKG-INFO
redlock_rf.egg-info/SOURCES.txt
redlock_rf.egg-info/dependency_links.txt
redlock_rf.egg-info/requires.txt
redlock_rf.egg-info/top_level.txt
tests/test_factory.py
tests/test_lock.py